[{"Number":"1","Player":"Conor McCollum","Year":"So","Position":"G","GP":"-","Goals":"-","Assists":"-","PIM":"-","Plus_Minus":"-","PPG":"-","SHG":"-","ENG":"-","GWG":"-","GTG":"-","Hat_Tricks":"-","Shots":"-","Points":"0"},{"Number":"4","Player":"Michael Zipp","Year":"Jr","Position":"D","GP":"24","Goals":"0","Assists":"2","PIM":"20","Plus_Minus":"+2","PPG":"0","SHG":"0","ENG":"0","GWG":"0","GTG":"0","Hat_Tricks":"0","Shots":"14","Points":"2"},{"Number":"7","Player":"Maurizio Colella","Year":"So","Position":"F","GP":"30","Goals":"9","Assists":"9","PIM":"28","Plus_Minus":"-1","PPG":"5","SHG":"0","ENG":"0","GWG":"0","GTG":"0","Hat_Tricks":"0","Shots":"71","Points":"18"},{"Number":"9","Player":"Ryan Foss","Year":"Jr","Position":"F","GP":"21","Goals":"2","Assists":"6","PIM":"6","Plus_Minus":"+3","PPG":"0","SHG":"0","ENG":"0","GWG":"1","GTG":"0","Hat_Tricks":"0","Shots":"28","Points":"8"},{"Number":"10","Player":"Liam Maaskant","Year":"Sr","Position":"D","GP":"28","Goals":"4","Assists":"11","PIM":"68","Plus_Minus":"+12","PPG":"1","SHG":"0","ENG":"0","GWG":"0","GTG":"0","Hat_Tricks":"0","Shots":"62","Points":"15"},{"Number":"14","Player":"Alexander Lepkowski","Year":"Sr","Position":"D","GP":"23","Goals":"2","Assists":"4","PIM":"42","Plus_Minus":"+3","PPG":"1","SHG":"0","ENG":"1","GWG":"0","GTG":"0","Hat_Tricks":"0","Shots":"30","Points":"6"},{"Number":"15","Player":"TJ Fergus","Year":"So","Position":"D","GP":"24","Goals":"1","Assists":"5","PIM":"26","Plus_Minus":"+1","PPG":"1","SHG":"0","ENG":"0","GWG":"0","GTG":"0","Hat_Tricks":"0","Shots":"19","Points":"6"},{"Number":"16","Player":"Marc McNulty","Year":"Sr","Position":"D","GP":"6","Goals":"2","Assists":"0","PIM":"14","Plus_Minus":"+3","PPG":"1","SHG":"0","ENG":"0","GWG":"0","GTG":"0","Hat_Tricks":"0","Shots":"6","Points":"2"},{"Number":"18","Player":"Eric Henderson","Year":"Fr.","Position":"F","GP":"30","Goals":"2","Assists":"14","PIM":"8","Plus_Minus":"+9","PPG":"0","SHG":"0","ENG":"0","GWG":"0","GTG":"0","Hat_Tricks":"0","Shots":"37","Points":"16"},{"Number":"19","Player":"Jack Flaman","Year":"So","Position":"F","GP":"27","Goals":"10","Assists":"6","PIM":"16","Plus_Minus":"+8","PPG":"0","SHG":"2","ENG":"2","GWG":"3","GTG":"0","Hat_Tricks":"1","Shots":"75","Points":"16"},{"Number":"20","Player":"Jack McClelland","Year":"Jr","Position":"F","GP":"9","Goals":"0","Assists":"0","PIM":"20","Plus_Minus":"-4","PPG":"0","SHG":"0","ENG":"0","GWG":"0","GTG":"0","Hat_Tricks":"0","Shots":"3","Points":"0"},{"Number":"21","Player":"Garrett McFadden","Year":"So","Position":"D","GP":"28","Goals":"7","Assists":"21","PIM":"26","Plus_Minus":"+15","PPG":"2","SHG":"0","ENG":"0","GWG":"1","GTG":"0","Hat_Tricks":"0","Shots":"93","Points":"28"},{"Number":"23","Player":"Johnny Corneil","Year":"So","Position":"F","GP":"29","Goals":"7","Assists":"7","PIM":"22","Plus_Minus":"+8","PPG":"0","SHG":"1","ENG":"0","GWG":"1","GTG":"0","Hat_Tricks":"0","Shots":"68","Points":"14"},{"Number":"24","Player":"Mason McCarty","Year":"Fr.","Position":"F","GP":"24","Goals":"10","Assists":"10","PIM":"46","Plus_Minus":"-6","PPG":"5","SHG":"0","ENG":"0","GWG":"3","GTG":"0","Hat_Tricks":"0","Shots":"67","Points":"20"},{"Number":"28","Player":"Ross MacDougall","Year":"So","Position":"D","GP":"29","Goals":"3","Assists":"12","PIM":"6","Plus_Minus":"+6","PPG":"0","SHG":"0","ENG":"1","GWG":"1","GTG":"0","Hat_Tricks":"0","Shots":"51","Points":"15"},{"Number":"30","Player":"Dawson Carty","Year":"Jr.","Position":"G","GP":"6","Goals":"0","Assists":"0","PIM":"0","Plus_Minus":"+0","PPG":"0","SHG":"0","ENG":"0","GWG":"0","GTG":"0","Hat_Tricks":"0","Shots":"0","Points":"0"},{"Number":"34","Player":"Stephen Harper","Year":"Sr","Position":"F","GP":"23","Goals":"9","Assists":"20","PIM":"24","Plus_Minus":"+10","PPG":"1","SHG":"0","ENG":"0","GWG":"2","GTG":"0","Hat_Tricks":"0","Shots":"72","Points":"29"},{"Number":"50","Player":"Logan Flodell","Year":"So","Position":"G","GP":"26","Goals":"0","Assists":"4","PIM":"2","Plus_Minus":"+0","PPG":"0","SHG":"0","ENG":"0","GWG":"0","GTG":"0","Hat_Tricks":"0","Shots":"0","Points":"4"},{"Number":"51","Player":"Tate Olson","Year":"So","Position":"D","GP":"22","Goals":"0","Assists":"6","PIM":"12","Plus_Minus":"+1","PPG":"0","SHG":"0","ENG":"0","GWG":"0","GTG":"0","Hat_Tricks":"0","Shots":"18","Points":"6"},{"Number":"55","Player":"Loch Morrison","Year":"So","Position":"D","GP":"23","Goals":"0","Assists":"2","PIM":"18","Plus_Minus":"-5","PPG":"0","SHG":"0","ENG":"0","GWG":"0","GTG":"0","Hat_Tricks":"0","Shots":"15","Points":"2"},{"Number":"67","Player":"Cristiano Digiacinto","Year":"Jr","Position":"F","GP":"30","Goals":"20","Assists":"17","PIM":"80","Plus_Minus":"+13","PPG":"5","SHG":"2","ENG":"2","GWG":"2","GTG":"0","Hat_Tricks":"2","Shots":"112","Points":"37"},{"Number":"71","Player":"Rodney Southam","Year":"Jr","Position":"F","GP":"20","Goals":"5","Assists":"8","PIM":"46","Plus_Minus":"+5","PPG":"2","SHG":"0","ENG":"0","GWG":"0","GTG":"0","Hat_Tricks":"0","Shots":"47","Points":"13"},{"Number":"76","Player":"Owen MacDonald","Year":"Jr","Position":"F","GP":"20","Goals":"10","Assists":"6","PIM":"16","Plus_Minus":"+3","PPG":"1","SHG":"0","ENG":"1","GWG":"3","GTG":"0","Hat_Tricks":"0","Shots":"36","Points":"16"},{"Number":"79","Player":"Jordy Stallard","Year":"So","Position":"F","GP":"25","Goals":"10","Assists":"13","PIM":"2","Plus_Minus":"+6","PPG":"2","SHG":"0","ENG":"0","GWG":"2","GTG":"1","Hat_Tricks":"0","Shots":"67","Points":"23"},{"Number":"89","Player":"Morgan Nauss","Year":"Fr.","Position":"D","GP":"14","Goals":"0","Assists":"2","PIM":"14","Plus_Minus":"+0","PPG":"0","SHG":"0","ENG":"0","GWG":"0","GTG":"0","Hat_Tricks":"0","Shots":"8","Points":"2"},{"Number":"","Player":"Totals","Year":"","Position":"","GP":"30","Goals":"113","Assists":"185","PIM":"570","Plus_Minus":"-","PPG":"27","SHG":"5","ENG":"7","GWG":"19","GTG":"1","Hat_Tricks":"3","Shots":"999","Points":"298"},{"Number":"","Player":"Opponent","Year":"","Position":"","GP":"30","Goals":"92","Assists":"155","PIM":"575","Plus_Minus":"-","PPG":"26","SHG":"3","ENG":"5","GWG":"11","GTG":"1","Hat_Tricks":"0","Shots":"1022","Points":"247"}]