[{"name":"Reilly Baker","yr":"Second","club":"North York Aquatics Club","town":"Toronto, ON"},{"name":"Ally Bennett","yr":"First","club":"Halton Hills Blue Fins","town":"Georgetown, ON"},{"name":"Mary Brown","yr":"Third","club":"Yarmouth Y Whitecaps Club","town":"Yarmouth, NS"},{"name":"Cali Bruce","yr":"Third","club":"","town":"Halifax, NS"},{"name":"Elyott Chang","yr":"Third","club":"","town":"Calgary, AB"},{"name":"Aaron Day","yr":"Second","club":"Pictou County Mariners Club","town":"New Glasgow, NS"},{"name":"Benito Di Nizio","yr":"Fourth","club":"RAMAC","town":"Toronto, ON"},{"name":"Bailey Dowell","yr":"Fourth","club":"Greenwood Dolphins","town":"Wilmot, NS"},{"name":"Kassidy Hamilton","yr":"Fr","club":"Fredericton Aquanaut Swim Club","town":"Fredericton, NB"},{"name":"Guy Harrison-Murray","yr":"Fourth","club":"Australian Dolphins Swim Team","town":"Perth, AUS"},{"name":"Benjamin Henger","yr":"Fifth","club":"Wolfville Tritons Swim Club","town":"Windsor, NS"},{"name":"Cameron Ingo","yr":"Fr","club":"Ernestown Barracuda Swim Club","town":"Sydenham, ON"},{"name":"Hannah Keay","yr":"Fourth","club":"Kingston Blue Marlins","town":"Kingston, ON"},{"name":"Shane Kenny","yr":"Second","club":"Blast Swim Team","town":"Bathurst, NB"},{"name":"Grier Kershaw","yr":"Second","club":"Orillia Channel Cats","town":"Barrie, ON"},{"name":"Lia Lancaster","yr":"Third","club":"","town":"Victoria, BC"},{"name":"Aubrey Landry","yr":"Third","club":"Shearwater Bluefins Swim Club","town":"Lawrencetown, NS"},{"name":"Owen Landry","yr":"Fourth","club":"Dartmouth Crusaders Swim Club","town":"Dartmouth, NS"},{"name":"Sarah Macdougall","yr":"Third","club":"Dartmouth Crusaders Swim Club","town":"Bedford, NS"},{"name":"Natalie Mason","yr":"Fourth","club":"Orangeville Otters","town":"Orangeville, ON"},{"name":"Sadie McAlear","yr":"Second","club":"Cornwall Sea Lions Swim Club","town":"Long Sault, ON"},{"name":"Holly McCool","yr":"Fr","club":"Orillia Channel Cats","town":"Severn, ON"},{"name":"Thomas McMillan","yr":"First","club":"Upper Canada River Otters","town":"Brockville, ON"},{"name":"Elisabeth Morrison","yr":"Second","club":"Fredericton H.S.","town":"Fredericton, NB"},{"name":"Sophia Munoz","yr":"Second","club":"Frontenac Secondary School","town":"Kingston, ON"},{"name":"Maddie Murray","yr":"Second","club":"Fighting Koalas Triathlon Team","town":"Burlington, ON"},{"name":"Joshua Nowlan","yr":"Fourth","club":"ROC Swimming","town":"Ottawa, ON"},{"name":"Molly Parker","yr":"Third","club":"St Margaret's Bay Breakers","town":"Halifax, NS"},{"name":"Jessica Pelletier","yr":"Fourth","club":"FAST","town":"Fredericton, NB"},{"name":"Lucas Perkins","yr":"Second","club":"Nepean Kanata Barracudas Swimming","town":"Ottawa, ON"},{"name":"Daeton Pitre","yr":"Fr","club":"","town":""},{"name":"Brett Russell","yr":"Fourth","club":"Halton Hills Blue Fins","town":"Georgetown, ON"},{"name":"Dean Sangster","yr":"Second","club":"Truro Centurions Swimming Club","town":"Truro, NS"},{"name":"Gordon Shortt","yr":"Second","club":"Norfolk Hammerhead Aquatic Club","town":"Simcoe, ON"},{"name":"Sylvia Thibault","yr":"Third","club":"Yarmouth Y Whitecaps","town":"Ste. Anne du Ruisseau, NS"},{"name":"Gina Vaillancourt","yr":"Second","club":"Saint John Fundy Tide Swim Club","town":"Quispamsis, NB"},{"name":"Kelsea Vessey","yr":"Fourth","club":"Greater Ottawa Kingfish","town":"Orleans, ON"},{"name":"Andre Walcott","yr":"Second","club":"Mako Aquatics Club","town":"Nassau, Bahamas"},{"name":"Logan Way","yr":"Fourth","club":"Greenwood Dolphins","town":"Aylesford, NS"},{"name":"Samantha Williams","yr":"Fourth","club":"Charlottetown Bluefins","town":"Charlottetown, PE"}]